{
    "pagination": { 
        "count": 25, 
        "limit": 25, 
        "offset": 0, 
        "total": 10000 },
    "data": [
      {
        "author": "Maroosha Muzaffar",
        "category": "general",
        "country": "gb",
        "description": "Christie’s says piece, stolen from Longleat estate in 1995 and found in a plastic bag seven years later, expected to fetch upto £25m",
        "image": "https://static.independent.co.uk/2024/04/04/15/01HTMRX3YNMYC49WWPGK0MS5HK.jpg?width=1200&auto=webp",
        "language": "en",
        "published_at": "2024-06-14T07:56:26Z",
        "source": "Independent",
        "title": "Stolen Titian painting found at London bus stop put up for auction",
        "url": "https://www.independent.co.uk/news/uk/home-news/titian-painting-stolen-london-bus-stop-auction-b2562503.html"
      },
      {
        "author": "newsdesk@men-news.co.uk (Adam Everett , Paul Britton)",
        "category": "general",
        "country": "gb",
        "description": "They even apparently had the initials of the convicts tattooed on their bodies",
        "image": "https://i2-prod.manchestereveningnews.co.uk/incoming/article29352610.ece/ALTERNATES/s98/0_prison-workers2.jpg",
        "language": "en",
        "published_at": "2024-06-14T07:53:16Z",
        "source": "Manchester Evening News",
        "title": "Prison workers 'infatuated' with robbers smuggled 'sniff' and 'tiny phones' into jail for them",
        "url": "https://www.manchestereveningnews.co.uk/news/greater-manchester-news/prison-workers-infatuated-with-robbers-2935225"
      },
      {
        "author": "Ellie Muir",
        "category": "general",
        "country": "gb",
        "description": "Cast members shared tearful memories of working together",
        "image": "https://static.independent.co.uk/2024/06/14/08/newFile-3.jpg?width=1200&auto=webp",
        "language": "en",
        "published_at": "2024-06-14T07:52:51Z",
        "source": "Independent",
        "title": "The Sopranos cast reunite for 25th anniversary and share behind-the-scenes secrets",
        "url": "https://www.independent.co.uk/arts-entertainment/tv/news/sopranos-cast-watch-anniversary-tony-b2562559.html"
      },
      {
        "author": "reporters@dailyrecord.co.uk (Ryan Thom)",
        "category": "general",
        "country": "gb",
        "description": "Emergency crews including four ambulances rushed to the scene on Thursday night after a smash on a road next to Weeze Airport, near Dusseldorf.",
        "image": "https://i2-prod.dailyrecord.co.uk/incoming/article33028574.ece/ALTERNATES/s98/1_0AAAAAAAAAAEMFans__16.jpg",
        "language": "en",
        "published_at": "2024-06-14T07:52:23Z",
        "source": "Daily Record",
        "title": "Five Scotland fans injured in Germany horror crash",
        "url": "https://www.dailyrecord.co.uk/news/scottish-news/five-scotland-fans-inured-germany-33028564"
      },
      {
        "author": "Michael Jones",
        "category": "sports",
        "country": "gb",
        "description": "Follow all the live build-up and action from the Euro 2024 opening match between Germany and Scotland",
        "image": "https://static.independent.co.uk/2024/06/13/18/GettyImages-2157448892%20%281%29.jpg?width=1200&auto=webp",
        "language": "en",
        "published_at": "2024-06-14T07:51:23Z",
        "source": "The Independent - Sports",
        "title": "Germany vs Scotland LIVE: Team news and build-up for Euro 2024 opener",
        "url": "https://www.independent.co.uk/sport/football/germany-scotland-live-stream-score-euro-2024-b2562252.html"
      },
      {
        "author": "reporters@dailyrecord.co.uk (Sophie Buchan)",
        "category": "general",
        "country": "gb",
        "description": "Can you take home the £1m jackpot?",
        "image": "https://i2-prod.dailyrecord.co.uk/incoming/article33026507.ece/ALTERNATES/s98/0_maxresdefault.jpg",
        "language": "en",
        "published_at": "2024-06-14T07:50:53Z",
        "source": "Daily Record",
        "title": "Who Wants to Be a Millionaire? Try these questions to see if you'd win £1m jackpot",
        "url": "https://www.dailyrecord.co.uk/lifestyle/who-wants-millionaire-try-questions-33026397"
      },
      
        {
            "author": "Sport Staff",
            "category": "general",
            "country": "gb",
            "description": "As Germany prepare to host their first major men’s tournament since 2006, we look at the teams, players and moments that could define the Euros",
            "image": "https://static.independent.co.uk/2024/06/10/16/newFile-1.jpg?width=1200&auto=webp",
            "language": "en",
            "published_at": "2024-06-14T07:33:26Z",
            "source": "Independent",
            "title": "Euro 2024 predictions: Winner, Golden Boot, breakout star and more",
            "url": "https://www.independent.co.uk/sport/football/euro-2024-predictions-winner-golden-boot-b2562562.html"
          },
          {
            "author": "reporters@dailyrecord.co.uk (Debbie Hall)",
            "category": "general",
            "country": "gb",
            "description": "It will open its first site in Scotland in The Centre, Livingston this summer",
            "image": "https://i2-prod.dailyrecord.co.uk/incoming/article33028573.ece/ALTERNATES/s98/0_Cinnabon-finaljpeg.jpg",
            "language": "en",
            "published_at": "2024-06-14T07:31:57Z",
            "source": "Daily Record",
            "title": "World famous Cinnabon to open first Scottish shop in West Lothian",
            "url": "https://www.dailyrecord.co.uk/news/local-news/world-famous-cinnabon-open-first-33028561"
          },
          {
            "author": "Jacob Stolworthy",
            "category": "general",
            "country": "gb",
            "description": "Norman Reedus previously said the canine actor ‘made scenes better’",
            "image": "https://static.independent.co.uk/2024/06/14/08/newFile.jpg?width=1200&auto=webp",
            "language": "en",
            "published_at": "2024-06-14T07:24:15Z",
            "source": "Independent",
            "title": "The Walking Dead star pays tribute to ‘best TV buddy ever’ after dog co-star dies",
            "url": "https://www.independent.co.uk/arts-entertainment/tv/news/the-walking-dead-dog-daryl-dixon-b2562545.html"
          },
          {
            "author": "Kate Gill",
            "category": "general",
            "country": "gb",
            "description": "Two frogs were thrown a lavish wedding ceremony to \"appease the rain gods\" into ending sweltering heatwaves in north India as temperatures reached 45 degrees Celsius (113 degrees Fahrenheit).",
            "image": "https://static.independent.co.uk/2024/06/14/08/frog%20.jpg?width=1200&auto=webp",
            "language": "en",
            "published_at": "2024-06-14T07:22:57Z",
            "source": "Independent",
            "title": "Frog wedding held to appease Indian rain god during heatwave as temperatures hit 45C",
            "url": "https://www.independent.co.uk/tv/climate/heatwave-india-frog-wedding-rain-monsoon-b2562554.html"
          },
          {
            "author": null,
            "category": "general",
            "country": "gb",
            "description": "A court case taken against a notorious vegan activist has exposed the enormous amount of money she earns from OnlyFans and how little she seems to give to animal rights"
          
      },
      
{
  "author": null,
  "category": "general",
  "country": "gb",
  "description": "A court case taken against a notorious vegan activist has exposed the enormous amount of money she earns from OnlyFans and how little she seems to give to animal rights causes.",
  "image": "https://i.dailymail.co.uk/1s/2024/06/14/00/86101823-0-image-m-20_1718321371361.jpg",
  "language": "en",
  "published_at": "2024-06-14T07:20:50Z",
  "source": "Mail",
  "title": "Tash Peterson's finances in the spotlight at defamation trial",
  "url": "https://www.dailymail.co.uk/news/article-13528475/Tash-Peterson-vegan-activist-money-OnlyFans.html?ns_mchannel=rss&ns_campaign=1490&ito=1490"
},
{
  "author": null,
  "category": "general",
  "country": "gb",
  "description": "One of Hansen's former sides, Liverpool, took to their social media channels to announce the news on Sunday afternoon, sending their best wishes to the former defender and his family.",
  "image": "https://i.dailymail.co.uk/1s/2024/06/14/00/86102091-0-image-a-77_1718321436472.jpg",
  "language": "en",
  "published_at": "2024-06-14T07:20:43Z",
  "source": "Mail",
  "title": "Gordon Strachan pays tribute to Alan Hansen, 69, with his close friend and former team-mate seriously ill in hospital... as he brands the Liverpool legend 'one of the best players Scotland has ever seen'",
  "url": "https://www.dailymail.co.uk/sport/football/article-13528557/Gordon-Strachan-tribute-Alan-Hansen-ill-hospital-Liverpool-Scotland.html?ns_mchannel=rss&ns_campaign=1490&ito=1490"
},
{
  "author": null,
  "category": "general",
  "country": "gb",
  "description": "The Australian actress, 41, has reinvented herself as a conservative firebrand. Now she's behind a major push.",
  "image": "https://i.dailymail.co.uk/1s/2024/06/14/04/86106057-0-image-m-14_1718334061537.jpg",
  "language": "en",
  "published_at": "2024-06-14T07:15:57Z",
  "source": "Mail",
  "title": "Neighbours actress Holly Valance makes shock political move - after she became a breakout conservative star for slamming Australia as 'too woke' and ridiculing Greta Thunberg",
  "url": "https://www.dailymail.co.uk/news/article-13528891/Neighbours-actress-Holly-Valance-Trump-London.html?ns_mchannel=rss&ns_campaign=1490&ito=1490"
},
{
  "author": "newsdesk@men-news.co.uk (Ashlie Blakey)",
  "category": "general",
  "country": "gb",
  "description": "A number of services have been delayed or cancelled between Manchester Piccadilly and Stockport this morning",
  "image": "https://i2-prod.manchestereveningnews.co.uk/incoming/article29352398.ece/ALTERNATES/s98/0_ABNM_MEN_12092023_TRANSPENNINE_PICCADILLY_88115JPG.jpg",
  "language": "en",
  "published_at": "2024-06-14T07:13:10Z",
  "source": "Manchester Evening News",
  "title": "LIVE: Trains to and from Manchester Piccadilly halted due to 'trespass incident' - latest updates",
  "url": "https://www.manchestereveningnews.co.uk/news/greater-manchester-news/live-trains-manchester-piccadilly-halted-29352389"
},
{
    "author": "As told to Stevie Chick",
    "category": "entertainment",
    "country": "gb",
    "description": "The celebrated MC takes your questions on losing his brothers to muscular dystrophy, converting to Islam and making an album no one can listen to. What do you feel is the most important aspect to a truly great rapper? Is it flow, wordplay or storytelling? Or is it non-technical things like their worldview, their upbringing or the people they surround themselves with? Dylandep It’s all of the above. You gotta really practise and then you got to understand your flow, understand wordplay, how to use your vocabulary. It do depend on where you’re at in your life and the life that you’re living...",
    "image": "https://i.guim.co.uk/img/media/09eae505a1fca96d01c884bd7c134e19b87c1e75/0_281_1920_1152/master/1920.jpg?width=140&quality=85&auto=format&fit=max&s=e5d567fe5b989fd121177da8f84eccd4",
    "language": "en",
    "published_at": "2024-06-14T07:00:45Z",
    "source": "The Guardian",
    "title": "Wu-Tang Clan’s Ghostface Killah: ‘A group is hard to keep together – people get jealous’",
    "url": "https://www.theguardian.com/music/article/2024/jun/14/wu-tang-clan-ghostface-killah-questions"
  },
  {
    "author": "Michael Adams",
    "category": "general",
    "country": "gb",
    "description": "Devastating shake-up for soap fans.",
    "image": null,
    "language": "en",
    "published_at": "2024-06-14T07:58:55Z",
    "source": "Metro",
    "title": "Disaster for fans as no soaps will air tonight with Coronation Street and Emmerdale pulled from schedules",
    "url": "https://metro.co.uk/2024/06/14/no-soaps-air-tonight-corrie-emmerdale-pulled-schedules-21032562/"
  },
  {
    "author": "Bruce Archer",
    "category": "sports",
    "country": "gb",
    "description": "talkSPORT betting tips – Best football bets and expert advice for Friday 14 June",
    "image": null,
    "language": "en",
    "published_at": "2024-06-14T07:51:14Z",
    "source": "TalkSport",
    "title": "talkSPORT betting tips – Best football bets and expert advice for Friday 14 June",
    "url": "https://talksport.com/football/1919374/betting-tips-best-football-bets-friday-14-june/"
  },
  {
    "author": "Jack Cunningham",
    "category": "sports",
    "country": "gb",
    "description": "What does the Euro 2024 logo mean? UEFA choose bright colours and interesting design",
    "image": null,
    "language": "en",
    "published_at": "2024-06-14T07:47:33Z"
  },
{
  "source": "TalkSport",
  "title": "What does the Euro 2024 logo mean? UEFA choose bright colours and interesting design",
  "url": "https://talksport.com/football/1830433/euro-2024-logo-colours-design-meaning-uefa/"
},
{
  "author": "Jack Cunningham",
  "category": "sports",
  "country": "gb",
  "description": "Official Euro 2024 match ball sees UEFA and adidas introduce cutting edge ‘Fussballliebe’",
  "image": null,
  "language": "en",
  "published_at": "2024-06-14T07:45:55Z",
  "source": "TalkSport",
  "title": "Official Euro 2024 match ball sees UEFA and adidas introduce cutting edge ‘Fussballliebe’",
  "url": "https://talksport.com/football/1830288/euro-2024-official-match-ball-fussballliebe-uefa-adidas/"
},
{
  "author": "Calli Kitson",
  "category": "general",
  "country": "gb",
  "description": "The shock changes aren't over yet.",
  "image": null,
  "language": "en",
  "published_at": "2024-06-14T07:41:14Z",
  "source": "Metro",
  "title": "Major Hollyoaks star quits just months after long-awaited return as cast exodus continues",
  "url": "https://metro.co.uk/2024/06/14/hollyoaks-star-quits-just-months-return-cast-exodus-continues-21032487/"
},
{
  "author": "Katie Boyden",
  "category": "general",
  "country": "gb",
  "description": "Unlike most royal trips and visits the details of the visit weren't published in advance.",
  "image": null,
  "language": "en",
  "published_at": "2024-06-14T07:22:08Z",
  "source": "Metro",
  "title": "Prince William makes secret MI6 visit as Trooping the Colour approaches",
  "url": "https://metro.co.uk/2024/06/14/royals-latest-prince-william-visits-mi6-ahead-trooping-colour-21030095/"
},

      {
        "author": "Business Matters",
        "category": "business",
        "country": "gb",
        "description": "WorkL, renowned for the World’s Happiest Workplace List and The Sunday Times Best Places to Work, raises £2M Series A funding with Calculus Capital to accelerate international growth and enhance workplace happiness globallyRead more: WorkL Secures £2M Series A Funding from Calculus Capital to Propel Global Expansion",
        "image": null,
        "language": "en",
        "published_at": "2024-06-14T07:20:26Z",
        "source": "Business Matters | The Uk's Leading Sme Business Magazine",
        "title": "WorkL Secures £2M Series A Funding from Calculus Capital to Propel Global Expansion",
        "url": "https://bmmagazine.co.uk/get-funded/workl-secures-2m-series-a-funding-from-calculus-capital-to-propel-global-expansion/"
      },
      {
        "author": "Andrew Gaudion",
        "category": "general",
        "country": "gb",
        "description": "Tories ‘not worried’ after Reform UK overtakes party in poll for first time",
        "image": null,
        "language": "en",
        "published_at": "2024-06-14T07:20:11Z",
        "source": "Metro",
        "title": "Tories ‘not worried’ after Reform UK overtakes party in poll for first time",
        "url": "https://metro.co.uk/2024/06/14/general-election-latest-tories-not-worried-reform-overtakes-party-21030170/"
      },
      
      
      {
        "author": "Sam Corbishley",
        "category": "general",
        "country": "gb",
        "description": "It is unclear whether the inferno was the latest in a string of Ukrainian sabotage attacks of key Russian strategic facilities.",
        "image": null,
        "language": "en",
        "published_at": "2024-06-14T07:10:01Z",
        "source": "Metro",
        "title": "Mystery fire breaks out at Putin’s warplane factory",
        "url": "https://metro.co.uk/2024/06/14/ukraine-drone-strikes-russia-mysterious-fire-ignites-sukhoi-warplane-bureau-21032473/"
      },
      {
        "author": "Business Matters",
        "category": "business",
        "country": "gb",
        "description": "Analysts forecast a significant drop in oil prices to $60 a barrel by late 2025, promising lower petrol costs and airfares, while creating challenges for North Sea fossil fuel producers amid potential tax hikes.Read more: Oil Prices Predicted to Plunge to $60 by 2025, Bringing Relief to Drivers",
        "image": null,
        "language": "en",
        "published_at": "2024-06-14T07:05:24Z",
        "source": "Business Matters | The Uk's Leading Sme Business Magazine",
        "title": "Oil Prices Predicted to Plunge to $60 by 2025, Bringing Relief to Drivers",
        "url": "https://bmmagazine.co.uk/news/oil-prices-predicted-to-plunge-to-60-by-2025-bringing-relief-to-drivers/"
      }
      
    ]
  }